out/outlier.py
outlier_3327-1.0.0.dist-info/LICENSE
outlier_3327-1.0.0.dist-info/LICENSE.py
outlier_3327-1.0.0.dist-info/METADATA
outlier_3327-1.0.0.dist-info/WHEEL
outlier_3327-1.0.0.dist-info/entry_points.txt
outlier_3327-1.0.0.dist-info/top_level.txt
outlier_3327-1.0.0.dist-info/RECORD
