Metadata-Version: 2.1
Name: outlier-3327
Version: 1.0.0
Summary: 'OUTLIER ROW REMOVAL PACKAGE'
Home-page: UNKNOWN
Author: Manjot khaira
Author-email: khairamanjot2@gmail.com
License: MIT
Platform: UNKNOWN
Classifier: License :: OSI Approved :: MIT License
Classifier: Programming Language :: Python :: 3
Classifier: Programming Language :: Python :: 3.7
Requires-Dist: requests
